disunity/__init__.py
disunity/cache.py
disunity/embed.py
disunity/errors.py
disunity/identifiers.py
disunity/package.py
disunity/server.py
disunity/utils.py
disunity/models/__init__.py
disunity/models/attachment.py
disunity/models/components.py
disunity/models/context.py
disunity/models/interaction.py
disunity/models/member.py
disunity/models/message.py
disunity/models/user.py
disunity-0.1.17.dist-info/LICENSE
disunity-0.1.17.dist-info/METADATA
disunity-0.1.17.dist-info/WHEEL
disunity-0.1.17.dist-info/top_level.txt
disunity-0.1.17.dist-info/RECORD
