Metadata-Version: 2.1
Name: disunity
Version: 0.1.17
Summary: Python framework for Discord interactions using a web server
Author: Tadeo Murillo, 
Project-URL: Homepoge, https://github.com/murillotadeo/disunity
Project-URL: Bug Tracker, https://github.com/murillotadeo/disunity/issues
Classifier: Programming Language :: Python :: 3
Classifier: License :: OSI Approved :: MIT License
Classifier: Operating System :: OS Independent
Requires-Python: >=3.10.0
License-File: LICENSE
